yodo1/__init__.py
yodo1/__version__.py
yodo1/aio_pika.py
yodo1/logger.py
yodo1/progress.py
yodo1/pydantic.py
yodo1/sqlalchemy.py
yodo1/sso.py
yodo1/uvicorn.py
yodo1/rabbitmq/__init__.py
yodo1/rabbitmq/http_client.py
yodo1/rabbitmq/multi_thread.py
yodo1_toolkit-0.3.9.dist-info/METADATA
yodo1_toolkit-0.3.9.dist-info/WHEEL
yodo1_toolkit-0.3.9.dist-info/top_level.txt
yodo1_toolkit-0.3.9.dist-info/RECORD
