Metadata-Version: 2.1
Name: yodo1-toolkit
Version: 0.3.9
Summary: A Yodo1 Python Toolbox
Home-page: https://github.com/Yodo1Games/py-yodo1
Author: Eliyar Eziz
Author-email: eliyar@yodo1.com
Classifier: Programming Language :: Python :: 3
Classifier: License :: OSI Approved :: MIT License
Classifier: Operating System :: OS Independent
Requires-Python: >=3.6
Requires-Dist: pydantic (<2.0,>=1.8.1)
Requires-Dist: sqlalchemy (<2.0,>=1.3.23)
Requires-Dist: pymysql (<2,>=1.0.2)
Requires-Dist: psutil
Requires-Dist: elastic-apm
Requires-Dist: aio-pika (<7,>=6.8.0)
Requires-Dist: pika (<1.3,>=1.2.0)
Requires-Dist: fastapi (<1,>=0.63.0)
Requires-Dist: pyjwt[crypto] (<3,>=2.1.0)
Requires-Dist: requests (<3,>=2.25.1)
Requires-Dist: httpx[http2]
Requires-Dist: pretty-errors (<2,>=1.2.20)
Requires-Dist: colorlog (<7,>=6.6.0)
Requires-Dist: tenacity (==8.1.0)
Requires-Dist: types-aiofiles
Requires-Dist: types-cachetools
Requires-Dist: types-orjson
Requires-Dist: types-requests
Requires-Dist: types-ujson
